MANIFEST.in
README.rst
setup.cfg
setup.py
django_taxonomy.egg-info/PKG-INFO
django_taxonomy.egg-info/SOURCES.txt
django_taxonomy.egg-info/dependency_links.txt
django_taxonomy.egg-info/requires.txt
django_taxonomy.egg-info/top_level.txt
taxonomy/__init__.py
taxonomy/admin.py
taxonomy/models.py
taxonomy/tests.py
taxonomy/views.py